rq_scheduler/__init__.py
rq_scheduler/scheduler.py
rq_scheduler/utils.py
rq_scheduler/scripts/__init__.py
rq_scheduler/scripts/rqscheduler.py
rq_scheduler_ng-0.5.1.dist-info/DESCRIPTION.rst
rq_scheduler_ng-0.5.1.dist-info/METADATA
rq_scheduler_ng-0.5.1.dist-info/RECORD
rq_scheduler_ng-0.5.1.dist-info/WHEEL
rq_scheduler_ng-0.5.1.dist-info/entry_points.txt
rq_scheduler_ng-0.5.1.dist-info/metadata.json
rq_scheduler_ng-0.5.1.dist-info/top_level.txt
