Metadata-Version: 2.0
Name: rq-scheduler-ng
Version: 0.5.1
Summary: Provides job scheduling capabilities to RQ (Redis Queue)
Home-page: https://github.com/ui/rq-scheduler
Author: Selwin Ong
Author-email: selwin.ong@gmail.com
License: MIT
Platform: UNKNOWN
Classifier: Development Status :: 3 - Alpha
Classifier: Environment :: Console
Classifier: Intended Audience :: Developers
Classifier: License :: OSI Approved :: MIT License
Classifier: Operating System :: OS Independent
Classifier: Programming Language :: Python :: 2
Classifier: Programming Language :: Python :: 2.6
Classifier: Programming Language :: Python :: 2.7
Classifier: Programming Language :: Python :: 3
Classifier: Programming Language :: Python :: 3.3
Classifier: Topic :: Software Development :: Libraries :: Python Modules
Requires-Dist: rq (>=0.3.5)
